databooks/__init__.py
databooks/__main__.py
databooks/affirm.py
databooks/cli.py
databooks/common.py
databooks/config.py
databooks/conflicts.py
databooks/data_models/__init__.py
databooks/data_models/base.py
databooks/data_models/cell.py
databooks/data_models/notebook.py
databooks/data_models/rich_helpers.py
databooks/git_utils.py
databooks/logging.py
databooks/metadata.py
databooks/py.typed
databooks/recipes.py
databooks/tui.py
databooks/version.py
databooks-1.3.10.dist-info/entry_points.txt
databooks-1.3.10.dist-info/LICENSE
databooks-1.3.10.dist-info/WHEEL
databooks-1.3.10.dist-info/METADATA
databooks-1.3.10.dist-info/RECORD
