Metadata-Version: 2.1
Name: databooks
Version: 1.3.10
Summary: A CLI tool to resolve git conflicts and remove metadata in notebooks.
Home-page: https://datarootsio.github.io/databooks/
License: MIT
Keywords: jupyter-notebooks,cli
Author: Murilo Cunha
Author-email: murilo@dataroots.io
Requires-Python: >=3.7,<4.0
Classifier: License :: OSI Approved :: MIT License
Classifier: Programming Language :: Python :: 3
Classifier: Programming Language :: Python :: 3.7
Classifier: Programming Language :: Python :: 3.8
Classifier: Programming Language :: Python :: 3.9
Classifier: Programming Language :: Python :: 3.10
Classifier: Programming Language :: Python :: 3.11
Requires-Dist: GitPython (>=3.1.24,<4.0.0)
Requires-Dist: pydantic (>=2.3,<3.0)
Requires-Dist: rich (>=12.6.0,<13.0.0)
Requires-Dist: tomli (>=2.0.1,<3.0.0)
Requires-Dist: typer (>=0.4.0,<1.0.0)
Requires-Dist: typing-extensions (>=4.0.1,<5.0.0)
Project-URL: Repository, https://github.com/datarootsio/databooks/
